django_sitevars-2.0.0.dist-info/licenses/LICENSE
sitevars/__init__.py
sitevars/admin.py
sitevars/apps.py
sitevars/checks.py
sitevars/context_processors.py
sitevars/models.py
sitevars/migrations/0001_initial.py
sitevars/migrations/__init__.py
sitevars/templatetags/__init__.py
sitevars/templatetags/sitevars.py
django_sitevars-2.0.0.dist-info/METADATA
django_sitevars-2.0.0.dist-info/WHEEL
django_sitevars-2.0.0.dist-info/top_level.txt
django_sitevars-2.0.0.dist-info/RECORD
