Metadata-Version: 2.4
Name: django-sitevars
Version: 2.0.0
Summary: A Django app for managing site-wide variables.
Author-email: Vince Veselosky <vince@control-escape.com>
Project-URL: Homepage, https://github.com/veselosky/django-sitevars
Project-URL: Bug Tracker, https://github.com/veselosky/django-sitevars/issues
Classifier: Programming Language :: Python :: 3
Classifier: License :: OSI Approved :: Apache Software License
Classifier: Development Status :: 5 - Production/Stable
Classifier: Operating System :: OS Independent
Classifier: Framework :: Django
Requires-Python: >=3.8
License-File: LICENSE
Requires-Dist: django>=4.2
Provides-Extra: dev
Requires-Dist: coverage; extra == "dev"
Requires-Dist: django-debug-toolbar; extra == "dev"
Requires-Dist: django-environ; extra == "dev"
Requires-Dist: django-extensions; extra == "dev"
Requires-Dist: djlint; extra == "dev"
Requires-Dist: docutils>=0.19; extra == "dev"
Requires-Dist: pre-commit>=3.5.0; extra == "dev"
Dynamic: license-file
